pytorch_mnl/__init__.py
pytorch_mnl/_nbdev.py
pytorch_mnl/core.py
pytorch_mnl-0.0.1.dist-info/LICENSE
pytorch_mnl-0.0.1.dist-info/METADATA
pytorch_mnl-0.0.1.dist-info/WHEEL
pytorch_mnl-0.0.1.dist-info/entry_points.txt
pytorch_mnl-0.0.1.dist-info/top_level.txt
pytorch_mnl-0.0.1.dist-info/RECORD
