Metadata-Version: 2.1
Name: pytorch-mnl
Version: 0.0.1
Summary: A simple MNL package that uses pytorch under the hood.
Home-page: https://github.com/tcapelle/pytorch_mnl/tree/master/
Author: Thomas Capelle
Author-email: tcapelle@pm.me
License: Apache Software License 2.0
Keywords: pytorch logistic-regression mnl
Platform: UNKNOWN
Classifier: Development Status :: 3 - Alpha
Classifier: Intended Audience :: Developers
Classifier: Natural Language :: English
Classifier: Programming Language :: Python :: 3.8
Classifier: License :: OSI Approved :: Apache Software License
Requires-Python: >=3.8
Requires-Dist: pip
Requires-Dist: packaging
Requires-Dist: numpy
Requires-Dist: pandas
Requires-Dist: torch (>1.8)
Requires-Dist: fastprogress
Requires-Dist: fastcore
Provides-Extra: dev
